LoadScript/__init__.py
LoadScript/load_script.py
LoadScript-1.dist-info/METADATA
LoadScript-1.dist-info/WHEEL
LoadScript-1.dist-info/top_level.txt
LoadScript-1.dist-info/RECORD
